<root>
  <info>
    <xLength>2</xLength>
    <yLength>1</yLength>
    <originId>0</originId>
  </info>

  <cells>
    <cell id="0">
      <isStation>true</isStation>
      <floorLevel>0</floorLevel>
      <dirtLevel>0</dirtLevel>
      <northPath>UNKNOWN</northPath>
      <southPath>UNKNOWN</southPath>
      <eastPath>UNKNOWN</eastPath>
      <westPath>UNKNOWN</westPath>
    </cell>
    <cell id="1">
      <isStation>false</isStation>
      <floorLevel>0</floorLevel>
      <dirtLevel>0</dirtLevel>
      <northPath>UNKNOWN</northPath>
      <southPath>UNKNOWN</southPath>
      <eastPath>UNKNOWN</eastPath>
      <westPath>UNKNOWN</westPath>
    </cell>
  </cells>
</root>
